example_package_lth/__init__.py
example_package_lth/console.py
example_package_lth/wikipedia.py
example_package_lth-0.1.0.dist-info/entry_points.txt
example_package_lth-0.1.0.dist-info/LICENSE
example_package_lth-0.1.0.dist-info/WHEEL
example_package_lth-0.1.0.dist-info/METADATA
example_package_lth-0.1.0.dist-info/RECORD
