Metadata-Version: 2.1
Name: example-package-lth
Version: 0.1.0
Summary: An example Python package
Home-page: https://github.com/letuanhai/python-example-package-lth
License: MIT
Keywords: example
Author: letuanhai
Author-email: letuanhai@live.com
Requires-Python: >=3.9,<4.0
Classifier: License :: OSI Approved :: MIT License
Classifier: Programming Language :: Python :: 3
Classifier: Programming Language :: Python :: 3.10
Classifier: Programming Language :: Python :: 3.9
Requires-Dist: click (>=8.0.4,<9.0.0)
Requires-Dist: desert (>=2020.11.18,<2021.0.0)
Requires-Dist: marshmallow (>=3.15.0,<4.0.0)
Requires-Dist: requests (>=2.27.1,<3.0.0)
Project-URL: Repository, https://github.com/letuanhai/python-example-package-lth
